securo/__init__.py
securo/cli.py
securo/file_manager.py
securo/securo.py
securo/utils.py
tests/__init__.py
tests/test_securo.py
securo-1.0.0.dist-info/LICENSE
securo-1.0.0.dist-info/METADATA
securo-1.0.0.dist-info/WHEEL
securo-1.0.0.dist-info/entry_points.txt
securo-1.0.0.dist-info/top_level.txt
securo-1.0.0.dist-info/RECORD
