Metadata-Version: 2.1
Name: securo
Version: 1.0.0
Summary: UNKNOWN
Home-page: UNKNOWN
Author: Yusuf
Author-email: contact@yusuf.im
License: MIT
Keywords: securo,encryptor,file encryptor,folder encryptor,encryption,decryption,fernet
Platform: UNKNOWN
Classifier: Programming Language :: Python :: 3
Classifier: Operating System :: OS Independent
Requires-Python: >=3.8
License-File: LICENSE
Requires-Dist: cryptography (>=3.4.7)
Requires-Dist: typer (>=0.4.0)
